base_deployment_controller/__init__.py
base_deployment_controller/builder.py
base_deployment_controller/models/__init__.py
base_deployment_controller/models/api.py
base_deployment_controller/models/compose.py
base_deployment_controller/models/container.py
base_deployment_controller/models/deployment.py
base_deployment_controller/models/environment.py
base_deployment_controller/models/events.py
base_deployment_controller/models/task.py
base_deployment_controller/routers/__init__.py
base_deployment_controller/routers/api.py
base_deployment_controller/routers/container.py
base_deployment_controller/routers/deployment.py
base_deployment_controller/routers/environment.py
base_deployment_controller/services/__init__.py
base_deployment_controller/services/config.py
base_deployment_controller/services/status_event_manager.py
base_deployment_controller/services/task_manager.py
base_deployment_controller-0.2.0.dist-info/METADATA
base_deployment_controller-0.2.0.dist-info/WHEEL
base_deployment_controller-0.2.0.dist-info/top_level.txt
base_deployment_controller-0.2.0.dist-info/RECORD
