Metadata-Version: 2.4
Name: base-deployment-controller
Version: 0.2.0
Summary: REST API to control the basic operations of a deployment
Author: Tknika
License: Creative Commons Atribución-NoComercial (CC BY-NC)
Classifier: Development Status :: 3 - Alpha
Classifier: Intended Audience :: Developers
Requires-Python: >=3.8
Requires-Dist: fastapi>=0.128.0
Requires-Dist: uvicorn[standard]>=0.40.0
Requires-Dist: python-dotenv>=1.2.1
Requires-Dist: pyyaml>=6.0.3
Requires-Dist: websockets>=16.0
Requires-Dist: python-on-whales>=0.80.0
Provides-Extra: dev
Requires-Dist: pytest>=7.4.0; extra == "dev"
Requires-Dist: pytest-asyncio>=0.21.0; extra == "dev"
Requires-Dist: requests>=2.31.0; extra == "dev"
